odoo/addons/partner_contact_sale_info_propagation/README.rst
odoo/addons/partner_contact_sale_info_propagation/__init__.py
odoo/addons/partner_contact_sale_info_propagation/__manifest__.py
odoo/addons/partner_contact_sale_info_propagation/i18n/ca.po
odoo/addons/partner_contact_sale_info_propagation/i18n/de.po
odoo/addons/partner_contact_sale_info_propagation/i18n/es.po
odoo/addons/partner_contact_sale_info_propagation/i18n/fr.po
odoo/addons/partner_contact_sale_info_propagation/i18n/it.po
odoo/addons/partner_contact_sale_info_propagation/i18n/partner_contact_sale_info_propagation.pot
odoo/addons/partner_contact_sale_info_propagation/models/__init__.py
odoo/addons/partner_contact_sale_info_propagation/models/res_partner.py
odoo/addons/partner_contact_sale_info_propagation/readme/CONTRIBUTORS.md
odoo/addons/partner_contact_sale_info_propagation/readme/DESCRIPTION.md
odoo/addons/partner_contact_sale_info_propagation/readme/USAGE.md
odoo/addons/partner_contact_sale_info_propagation/static/description/icon.png
odoo/addons/partner_contact_sale_info_propagation/static/description/index.html
odoo/addons/partner_contact_sale_info_propagation/tests/__init__.py
odoo/addons/partner_contact_sale_info_propagation/tests/test_partner_contact_sale_info_propagation.py
odoo_addon_partner_contact_sale_info_propagation-17.0.1.0.0.2.dist-info/METADATA
odoo_addon_partner_contact_sale_info_propagation-17.0.1.0.0.2.dist-info/WHEEL
odoo_addon_partner_contact_sale_info_propagation-17.0.1.0.0.2.dist-info/top_level.txt
odoo_addon_partner_contact_sale_info_propagation-17.0.1.0.0.2.dist-info/RECORD
